selang
