Metadata-Version: 1.1
Name: selang
Version: 0.1.1
Summary: Python, ASP and JSON abstractions of the SpaceEngine modding language
Home-page: https://github.com/aluriak/se-lang
Author: Lucas Bourneuf
Author-email: lucas.bourneuf@laposte.net
License: GPL
Keywords: SpaceEngine,DSL,Answer Set Programming
Platform: UNKNOWN
Classifier: Development Status :: 4 - Beta
Classifier: Intended Audience :: Developers
Classifier: Intended Audience :: Other Audience
Classifier: Programming Language :: Python :: 3
Classifier: Programming Language :: Python :: 3.5
Classifier: Programming Language :: ASP
